lyrasense/__init__.py
lyrasense/lyrasense.py
lyrasense-0.0.2.dist-info/METADATA
lyrasense-0.0.2.dist-info/WHEEL
lyrasense-0.0.2.dist-info/licenses/LICENSE
lyrasense-0.0.2.dist-info/RECORD
