Metadata-Version: 2.3
Name: lyrasense
Version: 0.0.2
Summary: The Python SDK for the Lyrasense EO platform.
Project-URL: Homepage, https://www.lyrasense.com/
Author-email: Dimitrios Kirtsios <dimkirts@gmail.com>
License-File: LICENSE
Classifier: License :: OSI Approved :: MIT License
Classifier: Operating System :: OS Independent
Classifier: Programming Language :: Python :: 3
Requires-Python: >=3.11
Requires-Dist: requests>=2.25.0
